<?xml version="1.0" encoding="utf-8"?>
<odoo>

    <template id="land_phase_subproject_designer_template" name="Land Phase Subproject Designer">
        <t t-call="website.layout">
            <t t-set="title">Phase terrain - <t t-esc="project.name"/></t>
            <link rel="stylesheet" href="https://unpkg.com/leaflet@1.9.4/dist/leaflet.css"/>
            <link rel="stylesheet" href="https://cdnjs.cloudflare.com/ajax/libs/leaflet.draw/1.0.4/leaflet.draw.css"/>
            <style>
                #land_phase_map { height: 78vh; width: 100%; border-radius: 12px; background:#f3f3f3; }
                .toolbar { margin: 15px 0; padding: 12px; background: #f7f7f7; border-radius: 12px; }
                .search-row { display:flex; gap:8px; flex-wrap:wrap; align-items:center; margin-bottom:10px; }
                .search-row input { min-width:280px; }
                .status-line { margin-top:8px; font-size:13px; font-weight:600; }
                .unit-label { background: rgba(255,255,255,0.9); border: 1px solid #333; border-radius: 4px; padding: 2px 6px; font-size: 12px; font-weight: 700; color: #111; box-shadow: 0 1px 3px rgba(0,0,0,0.25); }
                .phase-label { background:transparent !important; border:none !important; box-shadow:none !important; font-size:42px; font-weight:900; color:rgba(255,255,255,0.28); text-transform:uppercase; letter-spacing:4px; text-shadow:2px 2px 4px rgba(0,0,0,0.45), -1px -1px 2px rgba(0,0,0,0.25); pointer-events:none; }
                .edit-area-box { display:none; position:absolute; top:12px; right:12px; z-index:1000; background:rgba(255,255,255,0.96); border:2px solid #222; border-radius:8px; padding:8px 12px; font-size:14px; font-weight:700; color:#111; box-shadow:0 2px 8px rgba(0,0,0,0.25); pointer-events:none; }
                .map-wrapper { position:relative; }
                .alert-info { min-height:38px; }
            </style>
            <div class="container-fluid my-4">
                <h3><t t-esc="main_project.name"/> — <t t-esc="project.name"/></h3>
                <div class="toolbar">
                    <div class="search-row">
                        <strong>Recherche terrain :</strong>
                        <input id="search_place" class="form-control" placeholder="Ex : Ivandry, Antananarivo ou -18.8792,47.5079"/>
                        <button type="button" id="btn_search_place" class="btn btn-secondary">Rechercher</button>
                        <button type="button" id="btn_use_position" class="btn btn-outline-secondary">Utiliser la position actuelle</button>
                    </div>
                    <div class="row g-2 align-items-end">
                        <div class="col-md-4">
                            <label class="form-label fw-bold">Dessiner un :</label>
                            <select id="draw_type" class="form-select">
                                <option value="phase">Phase</option>
                                <option value="unit">Lot</option>
                            </select>
                            <div class="alert alert-info py-1 px-2 mt-1 mb-0 d-flex align-items-center">
                                <strong class="me-1">Phase =</strong>
                                <span><t t-esc="project.name"/></span>
                            </div>
                        </div>
                        <div class="col-md-4">
                            <label class="form-label fw-bold">Lot à dessiner</label>
                            <select id="unit_select" class="form-select"></select>
                            <div class="d-flex align-items-center gap-2 mt-2 flex-wrap">
                                <div class="form-check mb-0">
                                    <input class="form-check-input" type="checkbox" id="divide_mother_lot"/>
                                    <label class="form-check-label" for="divide_mother_lot">Diviser le lot mère</label>
                                </div>
                                <input type="number" id="divide_count" class="form-control" min="1" style="width:90px;"/>
                            </div>
                        </div>
                        <div class="col-md-4">
                            <button type="button" id="btn_rename_selected" class="btn btn-secondary">Renommer</button>
                            <button type="button" id="btn_clear_selected" class="btn btn-danger">Supprimer dessin</button>
                            <button type="button" class="btn btn-dark mt-1" onclick="window.close();">Finaliser</button>
                        </div>
                    </div>
                    <div class="text-muted mt-2">Les autres phases du même projet sont affichées en gris et restent verrouillées. Seule la phase active et ses lots sont modifiables.</div>
                    <div class="status-line" id="status_line"></div>
                </div>
                <div class="map-wrapper">
                    <div id="land_phase_map"></div>
                    <div id="area_info" class="edit-area-box">Surface dessinée : 0 m²</div>
                </div>
            </div>

            <script src="https://unpkg.com/leaflet@1.9.4/dist/leaflet.js"></script>
            <script src="https://cdnjs.cloudflare.com/ajax/libs/leaflet.draw/1.0.4/leaflet.draw.js"></script>
            <script src="https://cdn.jsdelivr.net/npm/@turf/turf@6/turf.min.js"></script>
            <script>
                const RECORD_ID = <t t-esc="project.id"/>;
                const DATA_ROUTE = `/property/land-phase/subproject/data/${RECORD_ID}`;
                const SAVE_PHASE_ROUTE = `/property/land-phase/save-phase/subproject/${RECORD_ID}`;
                const CLEAR_PHASE_ROUTE = `/property/land-phase/clear-phase/subproject/${RECORD_ID}`;
                const SAVE_ROUTE = (lineId) =&gt; `/property/unit-map/save/${lineId}`;
                const CLEAR_ROUTE = (lineId) =&gt; `/property/unit-map/clear/${lineId}`;

                const map = L.map('land_phase_map').setView([-18.8792, 47.5079], 16);
                L.tileLayer('https://server.arcgisonline.com/ArcGIS/rest/services/World_Imagery/MapServer/tile/{z}/{y}/{x}', { attribution:'Tiles © Esri', maxZoom:19 }).addTo(map);
                const drawnItems = new L.FeatureGroup().addTo(map);
                const lockedItems = new L.FeatureGroup().addTo(map);

                let units = [];
                let unitLayers = [];
                let phaseLayer = null;
                let activeLayer = null;
                let activeEditHandler = null;
                const areaInfoBox = document.getElementById('area_info');

                const drawControl = new L.Control.Draw({edit:false, draw:{polyline:false, circle:false, circlemarker:false, marker:false, rectangle:true, polygon:{allowIntersection:false, showArea:true}}});
                map.addControl(drawControl);

                function rpc(route, params) { return fetch(route, {method:'POST', headers:{'Content-Type':'application/json'}, body: JSON.stringify({jsonrpc:'2.0', method:'call', params: params || {}})}).then(r =&gt; r.json()).then(r =&gt; r.result || r); }
                function setStatus(msg) { document.getElementById('status_line').innerText = msg || ''; }
                function toFeature(geojson) { if (!geojson) return null; if (geojson.type === 'Feature') return geojson; return {type:'Feature', properties:{}, geometry:geojson}; }
                function geometryFeature(geometry) { return {type:'Feature', properties:{}, geometry: geometry}; }
                function calculateArea(geometry) { try { return Math.round(turf.area(geometryFeature(geometry)) * 100) / 100; } catch(e) { return 0; } }
                function formatArea(area) { if (!area) return '0 m²'; if (area &gt;= 10000) return (area / 10000).toFixed(4) + ' ha (' + area.toFixed(2) + ' m²)'; return area.toFixed(2) + ' m²'; }
                function unitDisplayLabel(unit) { return unit.label || unit.code || unit.name || 'Lot'; }
                function stageLabel(stage) { if (!stage) return stage; const map = { draft: 'Brouillon', sold: 'Vendu', available: 'Disponible', booked: 'Réserv\u00E9', on_lease: 'En location', sale: 'En vente' }; return map[stage] || stage; }
                function styleFor(unit) { return {color:unit.color || '#6b7280', fillColor:unit.color || '#6b7280', weight:2, fillOpacity:0.45}; }
                function currentPhaseStyle() { return {color:'#dc2626', fillColor:'transparent', weight:4, fillOpacity:0, opacity:1}; }
                function lockedPhaseStyle() { return {color:'#6b7280', fillColor:'transparent', weight:2, fillOpacity:0, opacity:0.9, dashArray:'7,6'}; }
                function lockedUnitStyle(unit) { return {color:unit.color || '#9ca3af', fillColor:unit.color || '#9ca3af', weight:2, fillOpacity:0.22, opacity:0.85, dashArray:'4,4'}; }
                function findUnit(lineId) { return units.find(u =&gt; String(u.line_id) === String(lineId)); }
                function findLayer(lineId) { return unitLayers.find(l =&gt; String((l.meta || {}).line_id) === String(lineId)); }
                function popupHtml(unit) { return `&lt;b&gt;${unitDisplayLabel(unit)}&lt;/b&gt;&lt;br/&gt;Phase : ${unit.phase_name || '-'}&lt;br/&gt;Code : ${unit.code || '-'}&lt;br/&gt;Statut : ${stageLabel(unit.stage) || '-'}&lt;br/&gt;Surface fiche : ${unit.surface || 0}&lt;br/&gt;Prix : ${unit.price || 0}&lt;br/&gt;&lt;br/&gt;&lt;button type="button" class="btn btn-sm btn-primary js-edit-unit" data-line-id="${unit.line_id}"&gt;Modifier dessin&lt;/button&gt; &lt;button type="button" class="btn btn-sm btn-success js-save-unit" data-line-id="${unit.line_id}"&gt;Enregistrer&lt;/button&gt; &lt;button type="button" class="btn btn-sm btn-secondary js-rename-unit" data-line-id="${unit.line_id}"&gt;Renommer&lt;/button&gt; &lt;button type="button" class="btn btn-sm btn-danger js-clear-unit" data-line-id="${unit.line_id}"&gt;Supprimer&lt;/button&gt;`; }
                function refreshLayerText(layer, unit) { layer.unbindTooltip(); layer.bindTooltip(unitDisplayLabel(unit), {permanent:true, direction:'center', className:'unit-label'}); layer.unbindPopup(); layer.bindPopup(popupHtml(unit)); }
                function registerUnitLayer(layer, unit) { layer.meta = unit; layer.setStyle(styleFor(unit)); refreshLayerText(layer, unit); layer.on('click', function() { selectDrawnLot(layer); }); drawnItems.addLayer(layer); unitLayers.push(layer); }
                function selectDrawnLot(layer) { if (!layer || !layer.meta) return; activeLayer = layer; document.getElementById('draw_type').value = 'unit'; const select = document.getElementById('unit_select'); if (![...select.options].some(opt =&gt; String(opt.value) === String(layer.meta.line_id))) { const opt = document.createElement('option'); opt.value = layer.meta.line_id; opt.textContent = (layer.meta.code ? layer.meta.code + ' - ' : '') + unitDisplayLabel(layer.meta) + ' (dessiné)'; opt.dataset.drawn = '1'; select.appendChild(opt); } select.value = layer.meta.line_id; setStatus('Lot sélectionné : ' + unitDisplayLabel(layer.meta) + '. Vous pouvez modifier, renommer ou supprimer ce dessin.'); }
                function renameLot(lineId) { const unit = findUnit(lineId); if (!unit) { alert('Sélectionnez un lot dessiné.'); return; } const label = askUnitLabel(unit); if (!label) return; unit.label = label; const layer = findLayer(lineId); if (layer) { layer.meta = unit; refreshLayerText(layer, unit); saveLayer(layer); } }
                function registerCurrentPhase(layer) { if (phaseLayer &amp;&amp; drawnItems.hasLayer(phaseLayer)) drawnItems.removeLayer(phaseLayer); phaseLayer = layer; phaseLayer.meta = {type:'phase'}; phaseLayer.setStyle(currentPhaseStyle()); phaseLayer.bindTooltip('<t t-esc="project.name"/>', {permanent:true, direction:'center', className:'phase-label'}); drawnItems.addLayer(phaseLayer); }
                function registerLockedPhase(phase) { const feature = toFeature(phase.geojson); if (!feature) return; L.geoJSON(feature, {style:lockedPhaseStyle(), interactive:false, onEachFeature:function(f, layer) { layer.bindTooltip(phase.name, {permanent:true, direction:'center', className:'phase-label'}); lockedItems.addLayer(layer); }}); }
                function registerLockedUnit(unit) { const feature = toFeature(unit.geojson); if (!feature) return; L.geoJSON(feature, {style:lockedUnitStyle(unit), interactive:false, onEachFeature:function(f, layer) { layer.bindTooltip(unitDisplayLabel(unit), {permanent:true, direction:'center', className:'unit-label'}); lockedItems.addLayer(layer); }}); }
                function getRemainingUnits() { return units.filter(u =&gt; !u.geojson); }
                function getRemainingLotsCount() { return getRemainingUnits().length; }
                function updateDivideCountDefault() { const input = document.getElementById('divide_count'); if (!input) return; const remaining = getRemainingLotsCount(); const current = parseInt(input.value || 0); if (!current || current &gt; remaining) input.value = remaining || 1; input.max = remaining || 1; }
                function refreshSelect() { const select = document.getElementById('unit_select'); select.innerHTML = '&lt;option value=""&gt;Sélectionner un lot...&lt;/option&gt;'; getRemainingUnits().forEach(u =&gt; { const opt = document.createElement('option'); opt.value = u.line_id; opt.textContent = (u.code ? u.code + ' - ' : '') + unitDisplayLabel(u); select.appendChild(opt); }); updateDivideCountDefault(); }
                function askUnitLabel(unit) { const label = prompt("Introduire le label du lot :", unit.label || unit.code || unit.name || ''); if (!label || !label.trim()) { alert('Le label est obligatoire.'); return false; } return label.trim(); }
                function updateEditingAreaDisplay(layer) { if (!layer) return; const area = calculateArea(layer.toGeoJSON().geometry); setStatus('Surface dessinée : ' + formatArea(area)); if (areaInfoBox) { areaInfoBox.innerText = 'Surface dessinée : ' + formatArea(area); areaInfoBox.style.display = 'block'; } }
                function clearEditingAreaDisplay() { if (areaInfoBox) { areaInfoBox.style.display = 'none'; areaInfoBox.innerText = 'Surface dessinée : 0 m²'; } if (activeLayer &amp;&amp; activeEditHandler) activeLayer.off('edit', activeEditHandler); activeEditHandler = null; }
                function disableEditing(except) { unitLayers.forEach(l =&gt; { if (l !== except &amp;&amp; l.editing) l.editing.disable(); }); if (phaseLayer &amp;&amp; phaseLayer !== except &amp;&amp; phaseLayer.editing) phaseLayer.editing.disable(); clearEditingAreaDisplay(); }
                function enablePhaseEdit() { if (!phaseLayer) { setStatus('Aucun dessin de phase. Dessinez la phase active.'); return; } disableEditing(phaseLayer); if (phaseLayer.editing) phaseLayer.editing.enable(); activeLayer = phaseLayer; activeEditHandler = function() { updateEditingAreaDisplay(phaseLayer); }; phaseLayer.on('edit', activeEditHandler); updateEditingAreaDisplay(phaseLayer); }
                function enableEdit(lineId) { const layer = findLayer(lineId); if (!layer) { setStatus('Aucun dessin existant pour ce lot. Dessinez un nouveau polygone.'); return; } disableEditing(layer); if (layer.editing) layer.editing.enable(); activeLayer = layer; layer.closePopup(); document.getElementById('unit_select').value = lineId; activeEditHandler = function() { updateEditingAreaDisplay(layer); }; layer.on('edit', activeEditHandler); updateEditingAreaDisplay(layer); }
                function savePhaseLayer(layer) { if (!layer) { alert('Dessinez d’abord la phase.'); return; } const geometry = layer.toGeoJSON().geometry; rpc(SAVE_PHASE_ROUTE, {geojson:geometry}).then(res =&gt; { if (res.error) { alert(res.error); return; } if (layer.editing) layer.editing.disable(); clearEditingAreaDisplay(); activeLayer = null; document.getElementById('draw_type').value = 'unit'; setStatus('Phase enregistrée.'); }); }
                function saveLayer(layer) { if (!layer) return; const unit = layer.meta || findUnit(document.getElementById('unit_select').value); if (!unit) { alert('Sélectionnez un lot.'); return; } if (!unit.label) { const label = askUnitLabel(unit); if (!label) return; unit.label = label; } const geometry = layer.toGeoJSON().geometry; rpc(SAVE_ROUTE(unit.line_id), {geojson:geometry, label:unit.label}).then(res =&gt; { if (res.error) { alert(res.error); return; } unit.geojson = geometry; layer.meta = unit; refreshLayerText(layer, unit); if (layer.editing) layer.editing.disable(); clearEditingAreaDisplay(); activeLayer = null; refreshSelect(); setStatus('Lot enregistré : ' + unitDisplayLabel(unit)); }); }
                function clearSelected() { if (document.getElementById('draw_type').value === 'phase') { if (!confirm('Supprimer le dessin de la phase active ?')) return; rpc(CLEAR_PHASE_ROUTE, {}).then(() =&gt; location.reload()); return; } const lineId = document.getElementById('unit_select').value || (activeLayer &amp;&amp; activeLayer.meta ? activeLayer.meta.line_id : false); if (!lineId) { alert('Sélectionnez un lot.'); return; } if (!confirm('Supprimer le dessin de ce lot ?')) return; rpc(CLEAR_ROUTE(lineId), {}).then(() =&gt; location.reload()); }
                function validateMotherLotDivision() { const checkbox = document.getElementById('divide_mother_lot'); const input = document.getElementById('divide_count'); if (!checkbox || !checkbox.checked) return false; const count = parseInt(input.value || 0); const remaining = getRemainingLotsCount(); if (!count || count &lt; 1) { alert('Veuillez saisir un nombre de lots valide.'); return false; } if (count &gt; remaining) { alert('Impossible de diviser en ' + count + ' lots. Il ne reste que ' + remaining + ' lots disponibles dans cette phase.'); return false; } return true; }
                function splitMotherLotGeometry(geometry, count) { const feature = geometryFeature(geometry); const bbox = turf.bbox(feature); const minX = bbox[0], minY = bbox[1], maxX = bbox[2], maxY = bbox[3]; const width = maxX - minX; const height = maxY - minY; const geometries = []; for (let i = 0; i &lt; count; i++) { let clipBox; if (width &gt;= height) { const x1 = minX + (width / count) * i; const x2 = minX + (width / count) * (i + 1); clipBox = [x1, minY, x2, maxY]; } else { const y1 = minY + (height / count) * i; const y2 = minY + (height / count) * (i + 1); clipBox = [minX, y1, maxX, y2]; } const clipped = turf.bboxClip(feature, clipBox); if (clipped &amp;&amp; clipped.geometry) geometries.push(clipped.geometry); } return geometries; }
                function addGeneratedUnitLayer(unit, geometry) { const feature = toFeature(geometry); if (!feature) return; L.geoJSON(feature, {style:styleFor(unit), onEachFeature:function(f, layer) { registerUnitLayer(layer, unit); }}); }
                function saveDividedMotherLot(layer) { if (!validateMotherLotDivision()) return; const count = parseInt(document.getElementById('divide_count').value || 0); const remainingUnits = getRemainingUnits(); const targetUnits = remainingUnits.slice(0, count); const geometries = splitMotherLotGeometry(layer.toGeoJSON().geometry, count); if (geometries.length &lt; count) { alert('La division automatique n’a pas pu générer tous les lots. Essayez un polygone plus simple.'); return; } let chain = Promise.resolve(); targetUnits.forEach((unit, index) =&gt; { const geometry = geometries[index]; const label = unit.label || unit.code || unit.name || 'Lot'; chain = chain.then(() =&gt; rpc(SAVE_ROUTE(unit.line_id), {geojson:geometry, label:label}).then(res =&gt; { if (res.error) throw new Error(res.error); unit.geojson = geometry; unit.label = label; addGeneratedUnitLayer(unit, geometry); })); }); chain.then(() =&gt; { refreshSelect(); const remaining = getRemainingLotsCount(); setStatus(count + ' lots créés automatiquement. Il reste ' + remaining + ' lot(s) à dessiner.'); }).catch(err =&gt; { alert(err.message || 'Erreur pendant la division automatique.'); }); }

                rpc(DATA_ROUTE, {}).then(data =&gt; {
                    if (data.error) { setStatus(data.error); return; }
                    map.setView([data.project.latitude || -18.8792, data.project.longitude || 47.5079], data.project.zoom || 16);
                    (data.other_phases || []).forEach(registerLockedPhase);
                    (data.other_units || []).forEach(registerLockedUnit);
                    const currentFeature = toFeature(data.current_phase ? data.current_phase.geojson : null);
                    if (currentFeature) L.geoJSON(currentFeature, {style:currentPhaseStyle(), onEachFeature:function(f, layer) { registerCurrentPhase(layer); }});
                    units = data.units || [];
                    refreshSelect();
                    units.forEach(u =&gt; { const feature = toFeature(u.geojson); if (!feature) return; L.geoJSON(feature, {style:styleFor(u), onEachFeature:function(f, layer) { registerUnitLayer(layer, u); }}); });
                    const all = new L.FeatureGroup([...drawnItems.getLayers(), ...lockedItems.getLayers()]);
                    if (all.getLayers().length) map.fitBounds(all.getBounds(), {padding:[20,20]});
                    document.getElementById('draw_type').value = phaseLayer ? 'unit' : 'phase';
                });

                document.getElementById('btn_search_place').addEventListener('click', function() { const q = document.getElementById('search_place').value; if (!q) { alert('Veuillez saisir un lieu ou des coordonnées.'); return; } const coords = q.split(',').map(x =&gt; parseFloat(x.trim())); if (coords.length === 2 &amp;&amp; !isNaN(coords[0]) &amp;&amp; !isNaN(coords[1])) { map.setView([coords[0], coords[1]], 18); return; } fetch(`https://nominatim.openstreetmap.org/search?format=json&amp;limit=1&amp;q=${encodeURIComponent(q)}`).then(r =&gt; r.json()).then(results =&gt; { if (!results.length) { alert('Terrain introuvable.'); return; } map.setView([parseFloat(results[0].lat), parseFloat(results[0].lon)], 18); }); });
                document.getElementById('btn_use_position').addEventListener('click', function() { if (!navigator.geolocation) { alert('Géolocalisation non supportée par ce navigateur.'); return; } navigator.geolocation.getCurrentPosition(function(pos) { map.setView([pos.coords.latitude, pos.coords.longitude], 18); }); });
                map.on(L.Draw.Event.CREATED, function(event) { const drawType = document.getElementById('draw_type').value; if (drawType === 'phase') { if (phaseLayer) { alert('Cette phase est déjà dessinée. Utilisez “Modifier dessin” pour la modifier.'); return; } registerCurrentPhase(event.layer); savePhaseLayer(event.layer); return; } const divideCheckbox = document.getElementById('divide_mother_lot'); if (divideCheckbox &amp;&amp; divideCheckbox.checked) { saveDividedMotherLot(event.layer); return; } const lineId = document.getElementById('unit_select').value; if (!lineId) { alert('Sélectionnez d’abord un lot.'); return; } const unit = findUnit(lineId); if (!unit) return; const label = unit.label || askUnitLabel(unit); if (!label) return; unit.label = label; const old = findLayer(lineId); if (old) drawnItems.removeLayer(old); unitLayers = unitLayers.filter(l =&gt; String((l.meta || {}).line_id) !== String(lineId)); registerUnitLayer(event.layer, unit); saveLayer(event.layer); });
                document.getElementById('btn_rename_selected').addEventListener('click', () =&gt; renameLot(document.getElementById('unit_select').value || (activeLayer &amp;&amp; activeLayer.meta ? activeLayer.meta.line_id : false)));
                document.getElementById('btn_clear_selected').addEventListener('click', clearSelected);
                document.addEventListener('click', function(ev) { const edit = ev.target.closest('.js-edit-unit'); const save = ev.target.closest('.js-save-unit'); const rename = ev.target.closest('.js-rename-unit'); const clear = ev.target.closest('.js-clear-unit'); if (edit) enableEdit(edit.dataset.lineId); if (save) saveLayer(findLayer(save.dataset.lineId)); if (rename) renameLot(rename.dataset.lineId); if (clear) { const layer = findLayer(clear.dataset.lineId); if (layer) selectDrawnLot(layer); clearSelected(); } });
                document.getElementById('divide_mother_lot').addEventListener('change', updateDivideCountDefault);
                document.getElementById('divide_count').addEventListener('change', function() { const remaining = getRemainingLotsCount(); const value = parseInt(this.value || 0); if (value &gt; remaining) { alert('Le nombre demandé dépasse les lots disponibles. Il reste ' + remaining + ' lot(s).'); this.value = remaining || 1; } });
            </script>
        </t>
    </template>

    <template id="land_phase_project_designer_template" name="Land Phase Project Designer">
        <t t-call="website.layout">
            <t t-set="title">Carte globale - <t t-esc="project.name"/></t>
            <link rel="stylesheet" href="https://unpkg.com/leaflet@1.9.4/dist/leaflet.css"/>
            <style>#land_phase_global_map { height:78vh; width:100%; border-radius:12px; background:#f3f3f3; } .unit-label { background:rgba(255,255,255,0.9); border:1px solid #333; border-radius:4px; padding:2px 6px; font-size:12px; font-weight:700; color:#111; box-shadow:0 1px 3px rgba(0,0,0,0.25); } .phase-label { background:transparent !important; border:none !important; box-shadow:none !important; font-size:42px; font-weight:900; color:rgba(255,255,255,0.28); text-transform:uppercase; letter-spacing:4px; text-shadow:2px 2px 4px rgba(0,0,0,0.45), -1px -1px 2px rgba(0,0,0,0.25); pointer-events:none; } .map-public-legend { display:flex; flex-wrap:wrap; align-items:center; gap:10px 22px; margin:0 0 14px; padding:12px 16px; background:#f5f7fa; border-left:4px solid #64748b; border-radius:4px; } .map-public-legend-item { display:inline-flex; align-items:center; justify-content:center; min-width:115px; padding:6px 12px; border-radius:3px; font-weight:700; color:#1f2937; white-space:nowrap; box-shadow:inset 0 0 0 1px rgba(0,0,0,0.18); } .map-public-legend-item.text-light { color:#fff; } .map-public-legend-help { flex:1 1 420px; margin:0; color:#475569; }</style>
            <div class="container-fluid my-4">
                <div class="d-flex justify-content-between align-items-center gap-3 mb-3">
                    <h3 class="mb-0"><t t-esc="project.name"/> — Carte globale des phases</h3>
                    <button t-if="designer_mode" type="button" class="btn btn-dark"
                        onclick="window.close();">Finaliser</button>
                </div>
                <div class="map-public-legend" aria-label="Légende des statuts">
                    <span class="map-public-legend-item" style="background:#22c55e;">Disponible</span>
                    <span class="map-public-legend-item" style="background:#f59e0b;">Réservé</span>
                    <span class="map-public-legend-item text-light" style="background:#8b5cf6;">En location</span>
                    <span class="map-public-legend-item text-light" style="background:#3b82f6;">En vente</span>
                    <span class="map-public-legend-item text-light" style="background:#ef4444;">Vendu</span>
                    <p class="map-public-legend-help">
                        Cliquez sur un bien pour consulter plus de détails ou nous contacter pour
                        effectuer une réservation.
                    </p>
                </div>
                <div id="land_phase_global_map"></div>
            </div>
            <script src="https://unpkg.com/leaflet@1.9.4/dist/leaflet.js"></script>
            <script>
                const DATA_ROUTE = `/property/land-phase/project/data/<t t-esc="project.id"/>`;
                const map = L.map('land_phase_global_map').setView([-18.8792, 47.5079], 16);
                L.tileLayer('https://server.arcgisonline.com/ArcGIS/rest/services/World_Imagery/MapServer/tile/{z}/{y}/{x}', { attribution:'Tiles © Esri', maxZoom:19 }).addTo(map);
                const all = new L.FeatureGroup().addTo(map);
                function rpc(route, params) { return fetch(route, {method:'POST', headers:{'Content-Type':'application/json'}, body: JSON.stringify({jsonrpc:'2.0', method:'call', params: params || {}})}).then(r =&gt; r.json()).then(r =&gt; r.result || r); }
                function toFeature(geojson) { if (!geojson) return null; if (geojson.type === 'Feature') return geojson; return {type:'Feature', properties:{}, geometry:geojson}; }
                function unitDisplayLabel(unit) { return unit.label || unit.code || unit.name || 'Lot'; }
                function stageLabel(stage) { if (!stage) return stage; const labels = { draft: 'Brouillon', sold: 'Vendu', available: 'Disponible', booked: 'Réserv\u00E9', on_lease: 'En location', sale: 'En vente' }; return labels[stage] || stage; }
                function formatNumber(value) { const number = Number(value || 0); return Number.isFinite(number) ? number.toLocaleString('fr-FR') : '0'; }
                function formatSurface(value) { return formatNumber(value) + ' m²'; }
                function phaseStyle() { return {color:'#6b7280', fillColor:'transparent', weight:3, fillOpacity:0, opacity:0.95, dashArray:'7,6'}; }
                function unitStyle(u) { return {color:u.color || '#6b7280', fillColor:u.color || '#6b7280', weight:2, fillOpacity:0.45}; }
                rpc(DATA_ROUTE, {exclude_draft: true}).then(data =&gt; { map.setView([data.project.latitude || -18.8792, data.project.longitude || 47.5079], data.project.zoom || 16); (data.other_phases || []).forEach(p =&gt; { const f = toFeature(p.geojson); if (!f) return; L.geoJSON(f, {style:phaseStyle(), onEachFeature:function(ff, layer) { layer.bindTooltip(p.name, {permanent:true, direction:'center', className:'phase-label'}); all.addLayer(layer); }}); }); (data.units || []).forEach(u =&gt; { const f = toFeature(u.geojson); if (!f) return; L.geoJSON(f, {style:unitStyle(u), onEachFeature:function(ff, layer) { layer.bindPopup(`&lt;b&gt;${unitDisplayLabel(u)}&lt;/b&gt;&lt;br/&gt;Phase : ${u.phase_name || '-'}&lt;br/&gt;Statut : ${stageLabel(u.stage) || '-'}&lt;br/&gt;Surface totale : ${formatSurface(u.surface)}&lt;br/&gt;Prix par m² : ${formatNumber(u.price_per_area)} Ariary/m²&lt;br/&gt;Prix : ${formatNumber(u.price)} Ariary`); layer.bindTooltip(unitDisplayLabel(u), {permanent:true, direction:'center', className:'unit-label'}); layer.on('mouseover', function() { layer.openPopup(); }); layer.on('mouseout', function() { layer.closePopup(); }); layer.on('click', function() { if (u.brocher_access_token) window.location.href = '/property-brochure/' + u.brocher_access_token; }); all.addLayer(layer); }}); }); if (all.getLayers().length) map.fitBounds(all.getBounds(), {padding:[20,20]}); });
            </script>
        </t>
    </template>

    <template id="land_phase_public_map_template" name="Land Phase Public Map">
        <t t-call="property_land_phase_management.land_phase_project_designer_template"/>
    </template>

    <template id="land_phase_preview_template" name="Land Phase Preview">
        <html>
            <head>
                <meta charset="utf-8"/>
                <link rel="stylesheet" href="https://unpkg.com/leaflet@1.9.4/dist/leaflet.css"/>
                <style>html, body { margin:0; padding:0; width:100%; height:100%; overflow:hidden; background:#f3f3f3; } #land_phase_preview_map { height:520px; width:100%; background:#f3f3f3; } .unit-label { background:rgba(255,255,255,0.9); border:1px solid #333; border-radius:4px; padding:2px 6px; font-size:12px; font-weight:700; color:#111; box-shadow:0 1px 3px rgba(0,0,0,0.25); } .phase-label { background:transparent !important; border:none !important; box-shadow:none !important; font-size:42px; font-weight:900; color:rgba(255,255,255,0.28); text-transform:uppercase; letter-spacing:4px; text-shadow:2px 2px 4px rgba(0,0,0,0.45), -1px -1px 2px rgba(0,0,0,0.25); pointer-events:none; }</style>
            </head>
            <body>
                <div id="land_phase_preview_map"></div>
                <script src="https://unpkg.com/leaflet@1.9.4/dist/leaflet.js"></script>
                <script>
                    const DATA_ROUTE = '<t t-esc="data_route"/>';
                    const map = L.map('land_phase_preview_map').setView([-18.8792, 47.5079], 16);
                    L.tileLayer('https://server.arcgisonline.com/ArcGIS/rest/services/World_Imagery/MapServer/tile/{z}/{y}/{x}', { attribution:'Tiles © Esri', maxZoom:19 }).addTo(map);
                    const all = new L.FeatureGroup().addTo(map);
                    function rpc(route, params) { return fetch(route, {method:'POST', headers:{'Content-Type':'application/json'}, body: JSON.stringify({jsonrpc:'2.0', method:'call', params: params || {}})}).then(r =&gt; r.json()).then(r =&gt; r.result || r); }
                    function toFeature(geojson) { if (!geojson) return null; if (geojson.type === 'Feature') return geojson; return {type:'Feature', properties:{}, geometry:geojson}; }
                    function unitDisplayLabel(unit) { return unit.label || unit.code || unit.name || 'Lot'; }
                    function phaseStyle(active) { return {color: active ? '#dc2626' : '#6b7280', fillColor:'transparent', weight: active ? 4 : 2, fillOpacity:0, opacity:0.95, dashArray: active ? null : '7,6'}; }
                    function unitStyle(u) { return {color:u.color || '#6b7280', fillColor:u.color || '#6b7280', weight:2, fillOpacity:0.45}; }
                    rpc(DATA_ROUTE, {}).then(data =&gt; { map.setView([data.project.latitude || -18.8792, data.project.longitude || 47.5079], data.project.zoom || 16); if (data.current_phase) { const f = toFeature(data.current_phase.geojson); if (f) L.geoJSON(f, {style:phaseStyle(true), onEachFeature:function(ff, layer) { layer.bindTooltip(data.current_phase.name, {permanent:true, direction:'center', className:'phase-label'}); all.addLayer(layer); }}); } (data.other_phases || []).forEach(p =&gt; { const f = toFeature(p.geojson); if (!f) return; L.geoJSON(f, {style:phaseStyle(false), onEachFeature:function(ff, layer) { layer.bindTooltip(p.name, {permanent:true, direction:'center', className:'phase-label'}); all.addLayer(layer); }}); }); (data.other_units || []).forEach(u =&gt; { const f = toFeature(u.geojson); if (!f) return; L.geoJSON(f, {style:unitStyle(u), interactive:false, onEachFeature:function(ff, layer) { layer.bindTooltip(unitDisplayLabel(u), {permanent:true, direction:'center', className:'unit-label'}); all.addLayer(layer); }}); }); (data.units || []).forEach(u =&gt; { const f = toFeature(u.geojson); if (!f) return; L.geoJSON(f, {style:unitStyle(u), onEachFeature:function(ff, layer) { layer.bindTooltip(unitDisplayLabel(u), {permanent:true, direction:'center', className:'unit-label'}); all.addLayer(layer); }}); }); if (all.getLayers().length) map.fitBounds(all.getBounds(), {padding:[20,20]}); });
                </script>
            </body>
        </html>
    </template>

</odoo>
